paddle/__init__.py
paddle/batch.py
paddle/compat.py
paddle/sysconfig.py
paddle/version.py
paddle/dataset/__init__.py
paddle/dataset/cifar.py
paddle/dataset/common.py
paddle/dataset/conll05.py
paddle/dataset/image.py
paddle/dataset/imdb.py
paddle/dataset/imikolov.py
paddle/dataset/mnist.py
paddle/dataset/movielens.py
paddle/dataset/wmt14.py
paddle/dataset/wmt16.py
paddle/distributed/__init__.py
paddle/distributed/launch.py
paddle/distributed/launch_ps.py
paddle/fluid/__init__.py
paddle/fluid/annotations.py
paddle/fluid/average.py
paddle/fluid/backward.py
paddle/fluid/clip.py
paddle/fluid/communicator.py
paddle/fluid/compiler.py
paddle/fluid/core.py
paddle/fluid/core_noavx.pyd
paddle/fluid/data.py
paddle/fluid/data_feed_desc.py
paddle/fluid/data_feeder.py
paddle/fluid/dataset.py
paddle/fluid/debugger.py
paddle/fluid/default_scope_funcs.py
paddle/fluid/device_worker.py
paddle/fluid/distribute_lookup_table.py
paddle/fluid/dygraph_grad_clip.py
paddle/fluid/evaluator.py
paddle/fluid/executor.py
paddle/fluid/framework.py
paddle/fluid/graphviz.py
paddle/fluid/inferencer.py
paddle/fluid/initializer.py
paddle/fluid/input.py
paddle/fluid/install_check.py
paddle/fluid/io.py
paddle/fluid/layer_helper.py
paddle/fluid/layer_helper_base.py
paddle/fluid/lod_tensor.py
paddle/fluid/log_helper.py
paddle/fluid/metrics.py
paddle/fluid/net_drawer.py
paddle/fluid/nets.py
paddle/fluid/op.py
paddle/fluid/optimizer.py
paddle/fluid/parallel_executor.py
paddle/fluid/param_attr.py
paddle/fluid/profiler.py
paddle/fluid/reader.py
paddle/fluid/regularizer.py
paddle/fluid/trainer_desc.py
paddle/fluid/trainer_factory.py
paddle/fluid/unique_name.py
paddle/fluid/wrapped_decorator.py
paddle/fluid/contrib/__init__.py
paddle/fluid/contrib/inferencer.py
paddle/fluid/contrib/memory_usage_calc.py
paddle/fluid/contrib/op_frequence.py
paddle/fluid/contrib/trainer.py
paddle/fluid/contrib/decoder/__init__.py
paddle/fluid/contrib/decoder/beam_search_decoder.py
paddle/fluid/contrib/extend_optimizer/__init__.py
paddlepaddle_tiny-1.6.1.dist-info/METADATA
paddlepaddle_tiny-1.6.1.dist-info/WHEEL
paddlepaddle_tiny-1.6.1.dist-info/top_level.txt
paddlepaddle_tiny-1.6.1.dist-info/RECORD
